src/pipelined_relu.sv
`timescale 1ns / 1ps

module pipelined_relu #(
    parameter NUM_ELEMENTS = 4,
    parameter DATA_WIDTH = 16
)(
    input  logic clk,
    input  logic rst_n,
    input  logic [(NUM_ELEMENTS*DATA_WIDTH)-1:0] in_flat,
    output logic [(NUM_ELEMENTS*DATA_WIDTH)-1:0] out_flat
);

    // Internal arrays to make the math readable
    logic signed [DATA_WIDTH-1:0] in_unpacked  [NUM_ELEMENTS];
    logic signed [DATA_WIDTH-1:0] out_unpacked [NUM_ELEMENTS];

    // Combinational block to unpack the 64-bit flat bus into array slots
    genvar i;
    generate
        for (i = 0; i < NUM_ELEMENTS; i++) begin : unpack_pack
            assign in_unpacked[i] = in_flat[(i*DATA_WIDTH) +: DATA_WIDTH];
            assign out_flat[(i*DATA_WIDTH) +: DATA_WIDTH] = out_unpacked[i];
        end
    endgenerate

    // Sequential block: The Pipeline Registers
    integer j;
    always_ff @(posedge clk or negedge rst_n) begin
        if (!rst_n) begin
            for (j = 0; j < NUM_ELEMENTS; j++) begin
                out_unpacked[j] <= '0;
            end
        end else begin
            for (j = 0; j < NUM_ELEMENTS; j++) begin
                // ReLU Logic: Check the Most Significant Bit (Sign Bit)
                // If in_unpacked[j][15] is 1, the number is negative -> snap to 0
                // Otherwise, the number is positive -> pass it through
                if (in_unpacked[j][DATA_WIDTH-1]) begin
                    out_unpacked[j] <= '0;
                end else begin
                    out_unpacked[j] <= in_unpacked[j];
                end
            end
        end
    end

    // --- WAVEFORM DUMPING ---
    initial begin
        // Keep it simple: dump directly to the simulator's working directory
        $dumpfile("pipelined_relu.vcd");
        $dumpvars(0, pipelined_relu);
        
        // This will print to your terminal right before the Cocotb test starts
        $display("\n=======================================================");
        $display("WAVEFORM DUMP: Generating pipelined_relu.vcd inside sim_build/");
        $display("=======================================================\n");
    end

endmodule

pipelined_relu.vcd
$date
	Fri Feb 27 09:34:25 2026
$end
$version
	Icarus Verilog
$end
$timescale
	1ps
$end
$scope module pipelined_relu $end
$var wire 1 ! clk $end
$var wire 64 " in_flat [63:0] $end
$var wire 1 # rst_n $end
$var wire 64 $ out_flat [63:0] $end
$var parameter 32 % DATA_WIDTH $end
$var parameter 32 & NUM_ELEMENTS $end
$var integer 32 ' j [31:0] $end
$scope begin unpack_pack[0] $end
$var parameter 2 ( i $end
$upscope $end
$scope begin unpack_pack[1] $end
$var parameter 2 ) i $end
$upscope $end
$scope begin unpack_pack[2] $end
$var parameter 3 * i $end
$upscope $end
$scope begin unpack_pack[3] $end
$var parameter 3 + i $end
$upscope $end
$upscope $end
$enddefinitions $end
$comment Show the parameter values. $end
$dumpall
b11 +
b10 *
b1 )
b0 (
b100 &
b10000 %
$end
#0
$dumpvars
b100 '
b0 $
1#
b0 "
1!
$end
#5000
0!
#10000
b1111111111111010000000000001000000000000000001110000000000000010 "
b100 '
1!
#15000
0!
#20000
b1111111111110000000000000000000011111111111110110000000000000110 "
b1000000000000000001110000000000000010 $
b100 '
1!
#25000
0!
#30000
b1111111111111010111111111111111000000000000011010000000000001010 "
b110 $
b100 '
1!
#35000
0!
#40000
b1111111111111000000000000000101100000000000011101111111111110110 "
b11010000000000001010 $
b100 '
1!
#45000
0!
#50000
b110111111111111001111111111111110110000000000001111 "
b101100000000000011100000000000000000 $
b100 '
1!
#55000
0!
#60000
b0 "
b110000000000000000000000000000000000000000000001111 $
b100 '
1!
#65000
0!
#70000
b0 $
b100 '
1!
